cloud_pomodoro/__init__.py
cloud_pomodoro/core.py
cloud_pomodoro/log.py
cloud_pomodoro/server.py
cloud_pomodoro-0.1.1.dist-info/METADATA
cloud_pomodoro-0.1.1.dist-info/WHEEL
cloud_pomodoro-0.1.1.dist-info/top_level.txt
cloud_pomodoro-0.1.1.dist-info/RECORD
